odoo/addons/mail_template_substitute_account_move/README.rst
odoo/addons/mail_template_substitute_account_move/__init__.py
odoo/addons/mail_template_substitute_account_move/__manifest__.py
odoo/addons/mail_template_substitute_account_move/i18n/it.po
odoo/addons/mail_template_substitute_account_move/i18n/mail_template_substitute_account_move.pot
odoo/addons/mail_template_substitute_account_move/models/__init__.py
odoo/addons/mail_template_substitute_account_move/models/account_move.py
odoo/addons/mail_template_substitute_account_move/readme/CONTRIBUTORS.md
odoo/addons/mail_template_substitute_account_move/readme/DESCRIPTION.md
odoo/addons/mail_template_substitute_account_move/readme/ROADMAP.md
odoo/addons/mail_template_substitute_account_move/readme/USAGE.md
odoo/addons/mail_template_substitute_account_move/static/description/icon.png
odoo/addons/mail_template_substitute_account_move/static/description/icon.svg
odoo/addons/mail_template_substitute_account_move/static/description/index.html
odoo/addons/mail_template_substitute_account_move/tests/__init__.py
odoo/addons/mail_template_substitute_account_move/tests/test_mail_template_substitute_account_move.py
odoo_addon_mail_template_substitute_account_move-17.0.1.0.0.4.dist-info/METADATA
odoo_addon_mail_template_substitute_account_move-17.0.1.0.0.4.dist-info/WHEEL
odoo_addon_mail_template_substitute_account_move-17.0.1.0.0.4.dist-info/top_level.txt
odoo_addon_mail_template_substitute_account_move-17.0.1.0.0.4.dist-info/RECORD
