Metadata-Version: 2.1
Name: odoo-addon-mail_template_substitute_account_move
Version: 17.0.1.0.0.4
Requires-Python: >=3.10
Requires-Dist: odoo-addon-mail_template_substitute>=17.0dev,<17.1dev
Requires-Dist: odoo>=17.0a,<17.1dev
Summary: Module to support Mail Template Substitution for Account Move
Home-page: https://github.com/OCA/account-financial-tools
License: AGPL-3
Author: Sodexis, Odoo Community Association (OCA)
Author-email: support@odoo-community.org
Classifier: Programming Language :: Python
Classifier: Framework :: Odoo
Classifier: Framework :: Odoo :: 17.0
Classifier: License :: OSI Approved :: GNU Affero General Public License v3
